{
  "name": "${scope}/${package}",
  "version": "${version}",
  "description": "${description}",
  "type": "${type}",
  "main": "./publish/cjs/index.js",
  "module": "publish/mjs/index.js",
  "types": "publish/mjs/index.d.ts",
  "exports": {
    ".": {
      "import": "./publish/mjs/index.js",
      "require": "./publish/cjs/index.js"
    }
  },
  "scripts": {
    "test": "echo \"Error: no test specified\" && exit 1"
  },
  "repository": {
    "type": "git",
    "url": "git+https://github.com/FranzZemen/execution-context.git"
  },
  "keywords": [
    "Execution Context"
  ],
  "author": "Franz Zemen",
  "license": "MIT",
  "bugs": {
    "url": "https://github.com/FranzZemen/execution-context/issues"
  },
  "homepage": "https://github.com/FranzZemen/execution-context#readme",
  "devDependencies": {
    "@franzzemen/gulp-base": "^19.0.1",
    "@franzzemen/npmu": "^4.0.4",
    "@types/chai": "^4.3.4",
    "@types/mocha": "^10.0.0",
    "@types/moment": "^2.13.0",
    "@types/node": "^18.11.9",
    "@types/uuid": "^8.3.4",
    "chai": "^4.3.7",
    "gulp": "^4.0.2",
    "gulp-mocha": "^8.0.0",
    "mocha": "^10.1.0",
    "typescript": "^4.9.3"
  },
  "dependencies": {
  }
}
